llama_index/llms/meta/__init__.py
llama_index/llms/meta/base.py
llama_index_llms_meta-0.2.1.dist-info/METADATA
llama_index_llms_meta-0.2.1.dist-info/WHEEL
llama_index_llms_meta-0.2.1.dist-info/licenses/LICENSE
llama_index_llms_meta-0.2.1.dist-info/RECORD
