Metadata-Version: 2.4
Name: llama-index-llms-meta
Version: 0.2.1
Summary: llama-index llms meta llama integration
Author-email: Young Han <younghan@meta.com>
Maintainer: seyeong-han
License-Expression: MIT
License-File: LICENSE
Requires-Python: <4.0,>=3.9
Requires-Dist: llama-index-llms-openai-like<0.6,>=0.5.0
